<annotation>
	<folder>augment_output</folder>
	<filename>IMG_20200217_154535_371.jpg</filename>
	<path>D:\Het\ocr\augmented\augment_output\IMG_20200217_154535_371.jpg</path>
	<source>
		<database>Unknown</database>
	</source>
	<size>
		<width>5029</width>
		<height>4150</height>
		<depth>3</depth>
	</size>
	<segmented>0</segmented>
	<object>
		<name>lcd</name>
		<pose>Unspecified</pose>
		<truncated>0</truncated>
		<difficult>0</difficult>
		<bndbox>
			<xmin>2477</xmin>
			<ymin>935</ymin>
			<xmax>3564</xmax>
			<ymax>2355</ymax>
		</bndbox>
	</object>
	<object>
		<name>qr</name>
		<pose>Unspecified</pose>
		<truncated>0</truncated>
		<difficult>0</difficult>
		<bndbox>
			<xmin>1450</xmin>
			<ymin>2421</ymin>
			<xmax>1777</xmax>
			<ymax>2735</ymax>
		</bndbox>
	</object>
</annotation>
