<annotation>
	<folder>augment_output</folder>
	<filename>IMG_20200218_092348.jpg</filename>
	<path>D:\Het\ocr\augmented\augment_output\IMG_20200218_092348.jpg</path>
	<source>
		<database>Unknown</database>
	</source>
	<size>
		<width>2160</width>
		<height>4560</height>
		<depth>3</depth>
	</size>
	<segmented>0</segmented>
	<object>
		<name>qr</name>
		<pose>Unspecified</pose>
		<truncated>0</truncated>
		<difficult>0</difficult>
		<bndbox>
			<xmin>812</xmin>
			<ymin>3058</ymin>
			<xmax>1076</xmax>
			<ymax>3315</ymax>
		</bndbox>
	</object>
	<object>
		<name>lcd</name>
		<pose>Unspecified</pose>
		<truncated>0</truncated>
		<difficult>0</difficult>
		<bndbox>
			<xmin>469</xmin>
			<ymin>1358</ymin>
			<xmax>1454</xmax>
			<ymax>1886</ymax>
		</bndbox>
	</object>
</annotation>
